DESCRIPTION.rst
LICENSE
MANIFEST.in
README.md
setup.py
sandstone_jupyterhub_login/__init__.py
sandstone_jupyterhub_login/handlers.py
sandstone_jupyterhub_login.egg-info/PKG-INFO
sandstone_jupyterhub_login.egg-info/SOURCES.txt
sandstone_jupyterhub_login.egg-info/dependency_links.txt
sandstone_jupyterhub_login.egg-info/entry_points.txt
sandstone_jupyterhub_login.egg-info/not-zip-safe
sandstone_jupyterhub_login.egg-info/requires.txt
sandstone_jupyterhub_login.egg-info/top_level.txt