Metadata-Version: 1.1
Name: sandstone-jupyterhub-login
Version: 0.1.2
Summary: Sandstone JupyterHub Login
